kangaroo/__init__.py
kangaroo/core.py
kangaroo/utils.py
kangaroo-0.1.0.dist-info/LICENSE
kangaroo-0.1.0.dist-info/WHEEL
kangaroo-0.1.0.dist-info/METADATA
kangaroo-0.1.0.dist-info/RECORD
