Metadata-Version: 2.1
Name: kangaroo
Version: 0.1.0
Summary: Find the absolute path of the desired file in parent directories.
Home-page: https://github.com/f9n/kangaroo
License: UNKNOWN
Author: Fatih Sarhan
Author-email: f9n@protonmail.com
Requires-Python: >=3.5,<4.0
Classifier: Programming Language :: Python :: 3
Classifier: Programming Language :: Python :: 3.5
Classifier: Programming Language :: Python :: 3.6
Classifier: Programming Language :: Python :: 3.7
Project-URL: Repository, https://github.com/f9n/kangaroo
